relattrs/__init__.py
relattrs-0.0.5.dist-info/LICENSE
relattrs-0.0.5.dist-info/METADATA
relattrs-0.0.5.dist-info/WHEEL
relattrs-0.0.5.dist-info/top_level.txt
relattrs-0.0.5.dist-info/RECORD
