Metadata-Version: 2.1
Name: relattrs
Version: 0.0.5
Summary: Toolkit for working with nth order relational attributes in Python classes.
Home-page: https://github.com/nibblex/python-relattrs
Author: Sergio Rodríguez
Author-email: srodriguez3441@gmail.com
Maintainer: Sergio Rodríguez
Maintainer-email: srodriguez3441@gmail.com
License: MIT
Classifier: Intended Audience :: Developers
Classifier: License :: OSI Approved :: MIT License
Classifier: Operating System :: OS Independent
Classifier: Programming Language :: Python :: 3
Classifier: Programming Language :: Python :: 3.7
Classifier: Programming Language :: Python :: 3.8
Classifier: Programming Language :: Python :: 3.9
Classifier: Programming Language :: Python :: 3.10
Classifier: Programming Language :: Python :: 3.11
Classifier: Programming Language :: Python :: 3.12
Classifier: Programming Language :: Python :: 3.13
Classifier: Topic :: Software Development :: Libraries :: Python Modules
Requires-Python: >=3.7
License-File: LICENSE
